profit/__init__.py
profit/config.py
profit/defaults.py
profit/main.py
profit/al/__init__.py
profit/al/active_learning.py
profit/al/aquisition_functions.py
profit/al/mcmc_al.py
profit/al/simple_al.py
profit/run/__init__.py
profit/run/command.py
profit/run/interface.py
profit/run/local.py
profit/run/runner.py
profit/run/slurm.py
profit/run/worker.py
profit/run/zeromq.py
profit/sur/__init__.py
profit/sur/encoders.py
profit/sur/sur.py
profit/sur/ann/__init__.py
profit/sur/ann/artificial_neural_network.py
profit/sur/gp/__init__.py
profit/sur/gp/custom_surrogate.py
profit/sur/gp/gaussian_process.py
profit/sur/gp/gpy_surrogate.py
profit/sur/gp/sklearn_surrogate.py
profit/sur/gp/backend/__init__.py
profit/sur/gp/backend/gp_functions.py
profit/sur/gp/backend/init_kernels.py
profit/sur/gp/backend/python_kernels.py
profit/sur/linreg/__init__.py
profit/sur/linreg/chaospy_linreg.py
profit/sur/linreg/linear_regression.py
profit/ui/__init__.py
profit/ui/app.py
profit/ui/condhist.py
profit/ui/hist_utils.py
profit/util/__init__.py
profit/util/base_class.py
profit/util/component.py
profit/util/file_handler.py
profit/util/halton.py
profit/util/util.py
profit/util/variable.py
profit-0.6.dist-info/LICENSE.txt
profit-0.6.dist-info/METADATA
profit-0.6.dist-info/WHEEL
profit-0.6.dist-info/entry_points.txt
profit-0.6.dist-info/top_level.txt
profit-0.6.dist-info/RECORD
