Metadata-Version: 2.1
Name: profit
Version: 0.6
Summary: Probabilistic response model fitting with interactive tools
Home-page: https://github.com/redmod-team/profit
Author: Christopher Albert
Author-email: albert@tugraz.at
License: MIT
Project-URL: Issue Tracker, https://github.com/redmod-team/profit/issues
Project-URL: Documentation, https://profit.readthedocs.io/en/latest
Keywords: Parameter Study,Gaussian Process,Regression,HPC,Active Learning
Platform: UNKNOWN
Classifier: Development Status :: 3 - Alpha
Classifier: Programming Language :: Python :: 3
Classifier: Programming Language :: Python :: 3.7
Classifier: Programming Language :: Python :: 3.8
Classifier: Programming Language :: Python :: 3.9
Classifier: Programming Language :: Python :: 3.10
Classifier: Intended Audience :: Science/Research
Classifier: License :: OSI Approved :: MIT License
Classifier: Operating System :: POSIX :: Linux
Classifier: Topic :: Scientific/Engineering
Classifier: Topic :: Scientific/Engineering :: Visualization
Classifier: Framework :: Dash
Requires-Python: >=3.7
License-File: LICENSE.txt
Requires-Dist: numpy (<1.24,>=1.16.0)
Requires-Dist: scipy
Requires-Dist: matplotlib
Requires-Dist: sympy
Requires-Dist: pyyaml
Requires-Dist: chaospy
Requires-Dist: GPy
Requires-Dist: scikit-learn
Requires-Dist: pandas
Requires-Dist: h5py
Requires-Dist: dash (>=1.20.0)
Requires-Dist: tqdm
Requires-Dist: zmq
Requires-Dist: importlib-metadata ; python_version < "3.8"
Provides-Extra: dev
Requires-Dist: pytest ; extra == 'dev'
Requires-Dist: pytest-cov ; extra == 'dev'
Requires-Dist: pytest-reraise ; extra == 'dev'
Requires-Dist: pytest-depends ; extra == 'dev'
Requires-Dist: jupyter ; extra == 'dev'
Requires-Dist: pre-commit ; extra == 'dev'
Requires-Dist: black[jupyter] ; extra == 'dev'
Provides-Extra: docs
Requires-Dist: sphinx (>=1.8.3) ; extra == 'docs'
Requires-Dist: sphinx-math-dollar ; extra == 'docs'
Requires-Dist: sphinx-rtd-theme ; extra == 'docs'
Requires-Dist: sphinx-autoapi ; extra == 'docs'
Requires-Dist: sphinx-toolbox ; extra == 'docs'
Requires-Dist: nbsphinx ; extra == 'docs'
Requires-Dist: ipykernel ; extra == 'docs'
Requires-Dist: recommonmark (>=0.5.0) ; extra == 'docs'
Requires-Dist: cachecontrol (>=0.12.6) ; extra == 'docs'
Requires-Dist: lockfile (>=0.12.2) ; extra == 'docs'
Provides-Extra: gpu
Requires-Dist: torch ; extra == 'gpu'
Requires-Dist: gpytorch ; extra == 'gpu'
